poodle/__init__.py
poodle/__main__.py
poodle/cli.py
poodle/config.py
poodle/core.py
poodle/mutate.py
poodle/report.py
poodle/run.py
poodle/util.py
poodle/data_types/__init__.py
poodle/data_types/data.py
poodle/data_types/interfaces.py
poodle/data_types/work.py
poodle/mutators/__init__.py
poodle/mutators/calls.py
poodle/mutators/compare.py
poodle/mutators/constant.py
poodle/mutators/operators.py
poodle/mutators/unary_op.py
poodle/reporters/__init__.py
poodle/reporters/basic.py
poodle/reporters/html.py
poodle/runners/__init__.py
poodle/runners/command_line.py
poodle/templates/html-report-index.html.jinja
poodle/templates/html-report-module.html.jinja
poodle/templates/html-report.css
poodle/templates/html-report.html.jinja
poodle/templates/html-report.js
poodle/templates/html-report.scss
poodle/templates/poodle.gif
poodle/templates/poodle.ico
poodle/templates/poodle.svg
poodle-1.3.3.dist-info/LICENSE
poodle-1.3.3.dist-info/METADATA
poodle-1.3.3.dist-info/WHEEL
poodle-1.3.3.dist-info/entry_points.txt
poodle-1.3.3.dist-info/top_level.txt
poodle-1.3.3.dist-info/RECORD
